api_analytics/__init__.py
api_analytics/core.py
api_analytics/fastapi.py
fastapi_analytics-1.2.5.dist-info/licenses/LICENSE
fastapi_analytics-1.2.5.dist-info/METADATA
fastapi_analytics-1.2.5.dist-info/WHEEL
fastapi_analytics-1.2.5.dist-info/top_level.txt
fastapi_analytics-1.2.5.dist-info/RECORD
