Metadata-Version: 2.4
Name: fastapi-analytics
Version: 1.2.5
Summary: Monitoring and analytics for FastAPI applications.
Author-email: Tom Draper <tomjdraper1@gmail.com>
License: MIT License
Project-URL: repository, https://github.com/tom-draper/api-analytics
Keywords: analytics,api,dashboard,fastapi,middleware
Classifier: License :: OSI Approved :: MIT License
Classifier: Programming Language :: Python
Classifier: Programming Language :: Python :: 3
Requires-Python: >=3.6
License-File: LICENSE
Requires-Dist: fastapi
Requires-Dist: requests
Provides-Extra: build
Requires-Dist: build; extra == "build"
Requires-Dist: twine; extra == "build"
Provides-Extra: dev
Requires-Dist: pytest; extra == "dev"
Dynamic: license-file
